appreg/__init__.py
appreg/appreg.py
appreg/post_payloads.py
appreg/set_timestamp.py
ops_py_appreg-0.1.2.dist-info/LICENSE
ops_py_appreg-0.1.2.dist-info/METADATA
ops_py_appreg-0.1.2.dist-info/WHEEL
ops_py_appreg-0.1.2.dist-info/top_level.txt
ops_py_appreg-0.1.2.dist-info/RECORD
