Metadata-Version: 2.1
Name: ops-py-appreg
Version: 0.1.2
Summary: Post Key Vault Secrets report to webhook
License: MIT License
License-File: LICENSE
Requires-Dist: beautifulsoup4 ==4.12.3
Requires-Dist: certifi ==2024.8.30
Requires-Dist: charset-normalizer ==3.4.0
Requires-Dist: idna ==3.10
Requires-Dist: ops-py-message-handler ==1.0.7
Requires-Dist: ops-py-reports ==0.4.6
Requires-Dist: pip ==24.3.1
Requires-Dist: requests ==2.32.3
Requires-Dist: setuptools ==75.5.0
Requires-Dist: soupsieve ==2.6
Requires-Dist: urllib3 ==2.2.3
Requires-Dist: wheel ==0.45.0
